tempting/__init__.py
tempting/cli.py
tempting/defaults.py
tempting/freckles_adapter_tempting.py
tempting/frkl.info
tempting/tempting.py
tempting/external/temptings/.gitkeep
tempting/external/temptings/temptings-default-develop/LICENSE
tempting/external/temptings/temptings-default-develop/applications/terminal/editor/zile/zile-config.tempting
tempting/external/temptings/temptings-default-develop/devops/images/packer/docker-frecklet-packer-template.tempting
tempting/external/temptings/temptings-default-develop/devops/images/packer/lxd-frecklet-packer-template.tempting
tempting/external/temptings/temptings-default-develop/devops/orchestration/nomad/nomad-client-config.tempting
tempting/external/temptings/temptings-default-develop/devops/orchestration/nomad/nomad-config.tempting
tempting/external/temptings/temptings-default-develop/devops/orchestration/nomad/nomad-server-config.tempting
tempting/external/temptings/temptings-default-develop/devops/service-mesh/consul/consul-config.tempting
tempting/external/temptings/temptings-default-develop/devops/service-mesh/consul/consul-server-config.tempting
tempting/external/temptings/temptings-default-develop/freckles/frecklet.tempting
tempting/external/temptings/temptings-default-develop/security/secrets/hashicorp-vault/vault-config.tempting
tempting/external/temptings/temptings-default-develop/service/webserver/apache/apache-vhost.tempting
tempting/external/temptings/temptings-default-develop/service/webserver/nginx/nginx-server-block.tempting
tempting/external/temptings/temptings-default-develop/system/init/systemd/systemd-service-config.tempting
tempting/external/temptings/temptings-default-develop/system/init/systemd/systemd-service-unit.tempting
tempting-1.0.0.dist-info/AUTHORS.rst
tempting-1.0.0.dist-info/LICENSE
tempting-1.0.0.dist-info/METADATA
tempting-1.0.0.dist-info/WHEEL
tempting-1.0.0.dist-info/entry_points.txt
tempting-1.0.0.dist-info/top_level.txt
tempting-1.0.0.dist-info/RECORD
